aioavasho.py
aioavasho-0.0.5.dist-info/LICENSE
aioavasho-0.0.5.dist-info/METADATA
aioavasho-0.0.5.dist-info/WHEEL
aioavasho-0.0.5.dist-info/top_level.txt
aioavasho-0.0.5.dist-info/RECORD
